<?xml version="1.0" encoding="UTF-8" standalone="no"?>
<database name="viva_segura" schema="viva_segura" type="MySQL - 8.4.8">
   <tables>
      <table catalog="viva_segura" name="atendimento" numRows="0" remarks="" type="TABLE">
         <column autoUpdated="true" defaultValue="null" digits="0" id="0" name="id" nullable="false" remarks="" size="10" type="INT" typeCode="4"/>
         <column autoUpdated="false" defaultValue="null" digits="0" id="1" name="data_atendimento" nullable="false" remarks="" size="10" type="DATE" typeCode="91"/>
         <column autoUpdated="false" defaultValue="null" digits="0" id="2" name="horario" nullable="true" remarks="" size="8" type="TIME" typeCode="92"/>
         <column autoUpdated="false" defaultValue="null" digits="0" id="3" name="protocolo" nullable="false" remarks="" size="50" type="VARCHAR" typeCode="12"/>
         <column autoUpdated="false" defaultValue="null" digits="0" id="4" name="observacoes" nullable="true" remarks="" size="65535" type="TEXT" typeCode="-1"/>
         <column autoUpdated="false" defaultValue="null" digits="0" id="5" name="usuario_id" nullable="false" remarks="" size="10" type="INT" typeCode="4">
            <parent catalog="viva_segura" column="id" foreignKey="atendimento_ibfk_1" implied="false" onDeleteCascade="true" table="usuario"/>
         </column>
         <column autoUpdated="false" defaultValue="null" digits="0" id="6" name="profissional_id" nullable="false" remarks="" size="10" type="INT" typeCode="4">
            <parent catalog="viva_segura" column="id" foreignKey="atendimento_ibfk_2" implied="false" onDeleteCascade="false" table="profissional"/>
         </column>
         <column autoUpdated="false" defaultValue="CURRENT_TIMESTAMP" digits="0" id="7" name="created_at" nullable="true" remarks="" size="19" type="TIMESTAMP" typeCode="93"/>
         <primaryKey column="id" sequenceNumberInPK="1"/>
         <index name="PRIMARY" unique="true">
            <column ascending="true" name="id"/>
         </index>
         <index name="idx_atendimento_profissional" unique="false">
            <column ascending="true" name="profissional_id"/>
         </index>
         <index name="idx_atendimento_usuario" unique="false">
            <column ascending="true" name="usuario_id"/>
         </index>
         <index name="protocolo" unique="true">
            <column ascending="true" name="protocolo"/>
         </index>
      </table>
      <table catalog="viva_segura" name="curso" numRows="0" remarks="" type="TABLE">
         <column autoUpdated="true" defaultValue="null" digits="0" id="0" name="id" nullable="false" remarks="" size="10" type="INT" typeCode="4"/>
         <column autoUpdated="false" defaultValue="null" digits="0" id="1" name="nome" nullable="false" remarks="" size="100" type="VARCHAR" typeCode="12"/>
         <column autoUpdated="false" defaultValue="null" digits="0" id="2" name="descricao" nullable="true" remarks="" size="65535" type="TEXT" typeCode="-1"/>
         <column autoUpdated="false" defaultValue="null" digits="0" id="3" name="tipo" nullable="true" remarks="" size="50" type="VARCHAR" typeCode="12"/>
         <column autoUpdated="false" defaultValue="CURRENT_TIMESTAMP" digits="0" id="4" name="created_at" nullable="true" remarks="" size="19" type="TIMESTAMP" typeCode="93"/>
         <column autoUpdated="false" defaultValue="CURRENT_TIMESTAMP" digits="0" id="5" name="updated_at" nullable="true" remarks="" size="19" type="TIMESTAMP" typeCode="93"/>
         <primaryKey column="id" sequenceNumberInPK="1"/>
         <index name="PRIMARY" unique="true">
            <column ascending="true" name="id"/>
         </index>
      </table>
      <table catalog="viva_segura" name="denuncia" numRows="0" remarks="" type="TABLE">
         <column autoUpdated="true" defaultValue="null" digits="0" id="0" name="id" nullable="false" remarks="" size="10" type="INT" typeCode="4"/>
         <column autoUpdated="false" defaultValue="null" digits="0" id="1" name="descricao" nullable="false" remarks="" size="65535" type="TEXT" typeCode="-1"/>
         <column autoUpdated="false" defaultValue="null" digits="0" id="2" name="data_denuncia" nullable="false" remarks="" size="10" type="DATE" typeCode="91"/>
         <column autoUpdated="false" defaultValue="null" digits="0" id="3" name="horario" nullable="false" remarks="" size="8" type="TIME" typeCode="92"/>
         <column autoUpdated="false" defaultValue="null" digits="0" id="4" name="usuario_id" nullable="false" remarks="" size="10" type="INT" typeCode="4">
            <parent catalog="viva_segura" column="id" foreignKey="denuncia_ibfk_1" implied="false" onDeleteCascade="true" table="usuario"/>
         </column>
         <column autoUpdated="false" defaultValue="CURRENT_TIMESTAMP" digits="0" id="5" name="created_at" nullable="true" remarks="" size="19" type="TIMESTAMP" typeCode="93"/>
         <primaryKey column="id" sequenceNumberInPK="1"/>
         <index name="PRIMARY" unique="true">
            <column ascending="true" name="id"/>
         </index>
         <index name="idx_denuncia_usuario" unique="false">
            <column ascending="true" name="usuario_id"/>
         </index>
      </table>
      <table catalog="viva_segura" name="emergencia" numRows="0" remarks="" type="TABLE">
         <column autoUpdated="true" defaultValue="null" digits="0" id="0" name="id" nullable="false" remarks="" size="10" type="INT" typeCode="4"/>
         <column autoUpdated="false" defaultValue="null" digits="0" id="1" name="local_emergencia" nullable="false" remarks="" size="150" type="VARCHAR" typeCode="12"/>
         <column autoUpdated="false" defaultValue="null" digits="0" id="2" name="descricao" nullable="true" remarks="" size="65535" type="TEXT" typeCode="-1"/>
         <column autoUpdated="false" defaultValue="null" digits="0" id="3" name="horario" nullable="false" remarks="" size="8" type="TIME" typeCode="92"/>
         <column autoUpdated="false" defaultValue="null" digits="0" id="4" name="data_emergencia" nullable="false" remarks="" size="10" type="DATE" typeCode="91"/>
         <column autoUpdated="false" defaultValue="null" digits="0" id="5" name="usuario_id" nullable="false" remarks="" size="10" type="INT" typeCode="4">
            <parent catalog="viva_segura" column="id" foreignKey="emergencia_ibfk_1" implied="false" onDeleteCascade="true" table="usuario"/>
         </column>
         <column autoUpdated="false" defaultValue="CURRENT_TIMESTAMP" digits="0" id="6" name="created_at" nullable="true" remarks="" size="19" type="TIMESTAMP" typeCode="93"/>
         <primaryKey column="id" sequenceNumberInPK="1"/>
         <index name="PRIMARY" unique="true">
            <column ascending="true" name="id"/>
         </index>
         <index name="idx_emergencia_usuario" unique="false">
            <column ascending="true" name="usuario_id"/>
         </index>
      </table>
      <table catalog="viva_segura" name="emprego" numRows="0" remarks="" type="TABLE">
         <column autoUpdated="true" defaultValue="null" digits="0" id="0" name="id" nullable="false" remarks="" size="10" type="INT" typeCode="4"/>
         <column autoUpdated="false" defaultValue="null" digits="0" id="1" name="cargo" nullable="false" remarks="" size="100" type="VARCHAR" typeCode="12"/>
         <column autoUpdated="false" defaultValue="null" digits="0" id="2" name="setor" nullable="true" remarks="" size="100" type="VARCHAR" typeCode="12"/>
         <column autoUpdated="false" defaultValue="null" digits="0" id="3" name="descricao" nullable="true" remarks="" size="65535" type="TEXT" typeCode="-1"/>
         <column autoUpdated="false" defaultValue="null" digits="0" id="4" name="requisitos" nullable="true" remarks="" size="65535" type="TEXT" typeCode="-1"/>
         <column autoUpdated="false" defaultValue="CURRENT_TIMESTAMP" digits="0" id="5" name="created_at" nullable="true" remarks="" size="19" type="TIMESTAMP" typeCode="93"/>
         <column autoUpdated="false" defaultValue="CURRENT_TIMESTAMP" digits="0" id="6" name="updated_at" nullable="true" remarks="" size="19" type="TIMESTAMP" typeCode="93"/>
         <primaryKey column="id" sequenceNumberInPK="1"/>
         <index name="PRIMARY" unique="true">
            <column ascending="true" name="id"/>
         </index>
      </table>
      <table catalog="viva_segura" name="profissional" numRows="0" remarks="" type="TABLE">
         <column autoUpdated="true" defaultValue="null" digits="0" id="0" name="id" nullable="false" remarks="" size="10" type="INT" typeCode="4">
            <child catalog="viva_segura" column="profissional_id" foreignKey="atendimento_ibfk_2" implied="false" onDeleteCascade="false" table="atendimento"/>
         </column>
         <column autoUpdated="false" defaultValue="null" digits="0" id="1" name="nome" nullable="false" remarks="" size="100" type="VARCHAR" typeCode="12"/>
         <column autoUpdated="false" defaultValue="null" digits="0" id="2" name="sexo" nullable="true" remarks="" size="1" type="CHAR" typeCode="1"/>
         <column autoUpdated="false" defaultValue="null" digits="0" id="3" name="data_nascimento" nullable="true" remarks="" size="10" type="DATE" typeCode="91"/>
         <column autoUpdated="false" defaultValue="null" digits="0" id="4" name="especialidade" nullable="true" remarks="" size="100" type="VARCHAR" typeCode="12"/>
         <column autoUpdated="false" defaultValue="null" digits="0" id="5" name="telefone" nullable="true" remarks="" size="20" type="VARCHAR" typeCode="12"/>
         <column autoUpdated="false" defaultValue="null" digits="0" id="6" name="email" nullable="true" remarks="" size="100" type="VARCHAR" typeCode="12"/>
         <column autoUpdated="false" defaultValue="CURRENT_TIMESTAMP" digits="0" id="7" name="created_at" nullable="true" remarks="" size="19" type="TIMESTAMP" typeCode="93"/>
         <column autoUpdated="false" defaultValue="CURRENT_TIMESTAMP" digits="0" id="8" name="updated_at" nullable="true" remarks="" size="19" type="TIMESTAMP" typeCode="93"/>
         <primaryKey column="id" sequenceNumberInPK="1"/>
         <index name="PRIMARY" unique="true">
            <column ascending="true" name="id"/>
         </index>
         <index name="email" unique="true">
            <column ascending="true" name="email"/>
         </index>
      </table>
      <table catalog="viva_segura" name="servico" numRows="0" remarks="" type="TABLE">
         <column autoUpdated="true" defaultValue="null" digits="0" id="0" name="id" nullable="false" remarks="" size="10" type="INT" typeCode="4"/>
         <column autoUpdated="false" defaultValue="null" digits="0" id="1" name="nome" nullable="false" remarks="" size="100" type="VARCHAR" typeCode="12"/>
         <column autoUpdated="false" defaultValue="null" digits="0" id="2" name="descricao" nullable="true" remarks="" size="65535" type="TEXT" typeCode="-1"/>
         <column autoUpdated="false" defaultValue="null" digits="0" id="3" name="tipo" nullable="true" remarks="" size="50" type="VARCHAR" typeCode="12"/>
         <column autoUpdated="false" defaultValue="CURRENT_TIMESTAMP" digits="0" id="4" name="created_at" nullable="true" remarks="" size="19" type="TIMESTAMP" typeCode="93"/>
         <column autoUpdated="false" defaultValue="CURRENT_TIMESTAMP" digits="0" id="5" name="updated_at" nullable="true" remarks="" size="19" type="TIMESTAMP" typeCode="93"/>
         <primaryKey column="id" sequenceNumberInPK="1"/>
         <index name="PRIMARY" unique="true">
            <column ascending="true" name="id"/>
         </index>
      </table>
      <table catalog="viva_segura" name="usuario" numRows="0" remarks="" type="TABLE">
         <column autoUpdated="true" defaultValue="null" digits="0" id="0" name="id" nullable="false" remarks="" size="10" type="INT" typeCode="4">
            <child catalog="viva_segura" column="usuario_id" foreignKey="atendimento_ibfk_1" implied="false" onDeleteCascade="true" table="atendimento"/>
            <child catalog="viva_segura" column="usuario_id" foreignKey="denuncia_ibfk_1" implied="false" onDeleteCascade="true" table="denuncia"/>
            <child catalog="viva_segura" column="usuario_id" foreignKey="emergencia_ibfk_1" implied="false" onDeleteCascade="true" table="emergencia"/>
         </column>
         <column autoUpdated="false" defaultValue="null" digits="0" id="1" name="nome" nullable="false" remarks="" size="100" type="VARCHAR" typeCode="12"/>
         <column autoUpdated="false" defaultValue="null" digits="0" id="2" name="cpf" nullable="false" remarks="" size="11" type="CHAR" typeCode="1"/>
         <column autoUpdated="false" defaultValue="null" digits="0" id="3" name="data_nascimento" nullable="true" remarks="" size="10" type="DATE" typeCode="91"/>
         <column autoUpdated="false" defaultValue="null" digits="0" id="4" name="email" nullable="false" remarks="" size="100" type="VARCHAR" typeCode="12"/>
         <column autoUpdated="false" defaultValue="null" digits="0" id="5" name="telefone" nullable="true" remarks="" size="20" type="VARCHAR" typeCode="12"/>
         <column autoUpdated="false" defaultValue="null" digits="0" id="6" name="endereco" nullable="true" remarks="" size="150" type="VARCHAR" typeCode="12"/>
         <column autoUpdated="false" defaultValue="null" digits="0" id="7" name="tipo_sanguineo" nullable="true" remarks="" size="10" type="VARCHAR" typeCode="12"/>
         <column autoUpdated="false" defaultValue="null" digits="0" id="8" name="alergias" nullable="true" remarks="" size="255" type="VARCHAR" typeCode="12"/>
         <column autoUpdated="false" defaultValue="null" digits="0" id="9" name="nome_contato_emergencia" nullable="true" remarks="" size="100" type="VARCHAR" typeCode="12"/>
         <column autoUpdated="false" defaultValue="null" digits="0" id="10" name="telefone_contato_emergencia" nullable="true" remarks="" size="20" type="VARCHAR" typeCode="12"/>
         <column autoUpdated="false" defaultValue="CURRENT_TIMESTAMP" digits="0" id="11" name="created_at" nullable="true" remarks="" size="19" type="TIMESTAMP" typeCode="93"/>
         <column autoUpdated="false" defaultValue="CURRENT_TIMESTAMP" digits="0" id="12" name="updated_at" nullable="true" remarks="" size="19" type="TIMESTAMP" typeCode="93"/>
         <primaryKey column="id" sequenceNumberInPK="1"/>
         <index name="PRIMARY" unique="true">
            <column ascending="true" name="id"/>
         </index>
         <index name="cpf" unique="true">
            <column ascending="true" name="cpf"/>
         </index>
         <index name="email" unique="true">
            <column ascending="true" name="email"/>
         </index>
      </table>
   </tables>
</database>
